readretro_test1/__init__.py
readretro_test1/backup_eval.py
readretro_test1/eval.py
readretro_test1/eval_npath.py
readretro_test1/eval_single.py
readretro_test1/readretro.py
readretro_test1/retropath_eval.py
readretro_test1/run.py
readretro_test1/run_json.py
readretro_test1/run_mp.py
readretro_test1/scope2paths.py
readretro_test1/setup.py
readretro_test1/g2s/translate.py
readretro_test1/g2s/models/attention_xl.py
readretro_test1/g2s/models/dgcn.py
readretro_test1/g2s/models/graph2seq_series_rel.py
readretro_test1/g2s/models/graphfeat.py
readretro_test1/g2s/models/model_utils.py
readretro_test1/g2s/utils/chem_utils.py
readretro_test1/g2s/utils/data_utils.py
readretro_test1/g2s/utils/preprocess.py
readretro_test1/g2s/utils/rxn_graphs.py
readretro_test1/retro_star/api.py
readretro_test1/retro_star/backup_api.py
readretro_test1/retro_star/retriever.py
readretro_test1/retro_star/alg/__init__.py
readretro_test1/retro_star/alg/mol_node.py
readretro_test1/retro_star/alg/mol_tree.py
readretro_test1/retro_star/alg/molstar.py
readretro_test1/retro_star/alg/reaction_node.py
readretro_test1/retro_star/alg/syn_route.py
readretro_test1/retro_star/common/__init__.py
readretro_test1/retro_star/common/prepare_utils.py
readretro_test1/retro_star/common/smiles_to_fp.py
readretro_test1/retro_star/model/__init__.py
readretro_test1/retro_star/model/value_mlp.py
readretro_test1/retro_star/rdchiral/__init__.py
readretro_test1/retro_star/rdchiral/bonds.py
readretro_test1/retro_star/rdchiral/chiral.py
readretro_test1/retro_star/rdchiral/clean.py
readretro_test1/retro_star/rdchiral/initialization.py
readretro_test1/retro_star/rdchiral/main.py
readretro_test1/retro_star/rdchiral/template_extractor.py
readretro_test1/retro_star/rdchiral/utils.py
readretro_test1/retro_star/utils/__init__.py
readretro_test1/retro_star/utils/logger.py
readretro_test1/retroformer/dataset.py
readretro_test1/retroformer/translate.py
readretro_test1/retroformer/models/decoder.py
readretro_test2-1.0.0.dist-info/LICENSE
readretro_test2-1.0.0.dist-info/METADATA
readretro_test2-1.0.0.dist-info/WHEEL
readretro_test2-1.0.0.dist-info/top_level.txt
readretro_test2-1.0.0.dist-info/RECORD
